LICENSE
MANIFEST.in
README.rst
setup.py
classy_xlsx/__init__.py
classy_xlsx/columns.py
classy_xlsx/core.py
classy_xlsx/regions.py
classy_xlsx/workbook.py
classy_xlsx/worksheet.py
classy_xlsx.egg-info/PKG-INFO
classy_xlsx.egg-info/SOURCES.txt
classy_xlsx.egg-info/dependency_links.txt
classy_xlsx.egg-info/requires.txt
classy_xlsx.egg-info/top_level.txt