Metadata-Version: 1.1
Name: classy-xlsx
Version: 0.2.3
Summary: The package allows you to create xlsx files in style models Django ORM.
Home-page: https://github.com/suguby/classy_xlsx
Author: Shandrinov Vadim
Author-email: suguby@gmail.com
License: BSD License
Platform: UNKNOWN
Classifier: Development Status :: 4 - Beta
Classifier: License :: OSI Approved :: BSD License
Classifier: Programming Language :: Python
Classifier: Programming Language :: Python :: 2.7
